{"categories_6809637767543259144.md":"C9FmbC3A","categories_6809637769959178254.md":"rEO1weLi","categories_6809637771511070734.md":"DNdHjGha","categories_6809637772874219534.md":"0tJdDIrH","categories_6809637773935378440.md":"dCR4kDVG","categories_index.md":"C_4MQLNN","columns_7107151273765371941.md":"Bb4QnrTq","columns_7187392655192490043.md":"Bb4CJncG","columns_index.md":"BoqRPjrn","index.md":"B3T2qyrY","overview_index.md":"XgYPsuAZ","ranking_index.md":"5atEocFM","recent_index.md":"PH_O0GwU","years_2022.md":"Bl3JT-F7","years_2023.md":"CR_NH3uF","years_2024.md":"Bnp0BCwy","years_2025.md":"DOnZ9eBp"}
