{"index.md":"Da2wf2vd","years_2024.md":"ezcC4_ks","columns_7187392655192490043.md":"CGKvW3RZ","categories_6809637769959178254.md":"DQkjFFgZ","categories_6809637773935378440.md":"C5e5wlmB","ranking_index.md":"DtSR9vih","years_2023.md":"CsOrrK7C","columns_index.md":"B4eXthhz","categories_6809637772874219534.md":"Q15BErNh","recent_index.md":"CWPQrMGl","categories_6809637767543259144.md":"B7wYNzKr","categories_index.md":"DuThmSQY","overview_index.md":"B4LymsiA","years_2022.md":"DfzLlC-b","columns_7107151273765371941.md":"CZXMgmIQ"}
